classically/__init__.py
classically/cdd.py
classically/scatter.py
classically/score.py
classically/types.py
classically-1.0.4.dist-info/LICENSE
classically-1.0.4.dist-info/WHEEL
classically-1.0.4.dist-info/METADATA
classically-1.0.4.dist-info/RECORD
