Metadata-Version: 2.1
Name: classically
Version: 1.0.4
Summary: Classifier Comparison and Feature Analysis Tools in Python
Home-page: https://github.com/alienkrieg/classically
License: MIT
Keywords: machine learning,classification,analysis
Author: alienkrieg
Author-email: alienkrieg@gmail.com
Requires-Python: >=3.9,<3.10
Classifier: License :: OSI Approved :: MIT License
Classifier: Programming Language :: Python :: 3
Classifier: Programming Language :: Python :: 3.9
Requires-Dist: matplotlib (>=3.5.1,<4.0.0)
Requires-Dist: networkx (>=2.6.3,<3.0.0)
Requires-Dist: numpy (>=1.22.2,<2.0.0)
Requires-Dist: scikit-learn (>=1.1.2,<2.0.0)
Requires-Dist: scipy (>=1.8.0,<2.0.0)
Project-URL: Repository, https://github.com/alienkrieg/classically
